RTSDataBase/RTSDB.py
RTSDataBase/__init__.py
RTSDataBase/exceptions.py
RTSDataBase/typotest.py
RTSDB-3.3.dist-info/LICENCE
RTSDB-3.3.dist-info/METADATA
RTSDB-3.3.dist-info/WHEEL
RTSDB-3.3.dist-info/top_level.txt
RTSDB-3.3.dist-info/RECORD
