Metadata-Version: 2.1
Name: RTSDB
Version: 3.3
Summary: Create yourself a simple database with this package.
Home-page: https://github.com/RandomTimeLP/RTS_DataBase/
Author: RandomTimeTV
Author-email: dergepanzerte1@gmail.com
License: MIT with required credit to the author.
Keywords: database
Classifier: Development Status :: 3 - Alpha
Classifier: License :: OSI Approved :: MIT License
Classifier: Programming Language :: Python :: 3.6
Classifier: Programming Language :: Python :: 3.7
Classifier: Programming Language :: Python :: 3.8
Classifier: Programming Language :: Python :: 3.9
License-File: LICENCE
Requires-Dist: extradecorators
Requires-Dist: extrautilities
Requires-Dist: aiohttp
